napari_imagej/__init__.py
napari_imagej/java.py
napari_imagej/model.py
napari_imagej/napari.yml
napari_imagej/settings.py
napari_imagej/readers/trackMate_reader.py
napari_imagej/resources/__init__.py
napari_imagej/resources/export.svg
napari_imagej/resources/export_detailed.svg
napari_imagej/resources/gear.svg
napari_imagej/resources/imagej2-16x16-flat-disabled.png
napari_imagej/resources/imagej2-16x16-flat.png
napari_imagej/resources/import.svg
napari_imagej/resources/repl.svg
napari_imagej/types/enum_likes.py
napari_imagej/types/enums.py
napari_imagej/types/type_conversions.py
napari_imagej/types/type_hints.py
napari_imagej/types/type_utils.py
napari_imagej/types/widget_mappings.py
napari_imagej/types/converters/__init__.py
napari_imagej/types/converters/enum_likes.py
napari_imagej/types/converters/enums.py
napari_imagej/types/converters/images.py
napari_imagej/types/converters/labels.py
napari_imagej/types/converters/meshes.py
napari_imagej/types/converters/points.py
napari_imagej/types/converters/shapes.py
napari_imagej/types/converters/trackmate.py
napari_imagej/utilities/_module_utils.py
napari_imagej/utilities/event_subscribers.py
napari_imagej/utilities/events.py
napari_imagej/utilities/progress_manager.py
napari_imagej/widgets/info_bar.py
napari_imagej/widgets/layouts.py
napari_imagej/widgets/menu.py
napari_imagej/widgets/napari_imagej.py
napari_imagej/widgets/parameter_widgets.py
napari_imagej/widgets/repl.py
napari_imagej/widgets/result_runner.py
napari_imagej/widgets/result_tree.py
napari_imagej/widgets/searchbar.py
napari_imagej/widgets/widget_utils.py
napari_imagej-0.2.0.dist-info/LICENSE
napari_imagej-0.2.0.dist-info/METADATA
napari_imagej-0.2.0.dist-info/WHEEL
napari_imagej-0.2.0.dist-info/entry_points.txt
napari_imagej-0.2.0.dist-info/top_level.txt
napari_imagej-0.2.0.dist-info/RECORD
