Metadata-Version: 2.1
Name: napari-imagej
Version: 0.2.0
Summary: ImageJ functionality from napari
Author-email: ImageJ2 developers <ctrueden@wisc.edu>
License: BSD-2-Clause
Project-URL: homepage, https://github.com/imagej/napari-imagej
Project-URL: documentation, https://napari-imagej.readthedocs.io
Project-URL: source, https://github.com/imagej/napari-imagej
Project-URL: download, https://pypi.org/project/napari-imagej/#files
Project-URL: tracker, https://github.com/imagej/napari-imagej/issues
Keywords: java,imagej,imagej2,fiji,napari
Classifier: Development Status :: 4 - Beta
Classifier: Intended Audience :: Developers
Classifier: Intended Audience :: Science/Research
Classifier: Framework :: napari
Classifier: Programming Language :: Python :: 3 :: Only
Classifier: Programming Language :: Python :: 3.9
Classifier: Programming Language :: Python :: 3.10
Classifier: Programming Language :: Python :: 3.11
Classifier: Programming Language :: Python :: 3.12
Classifier: Operating System :: Microsoft :: Windows
Classifier: Operating System :: Unix
Classifier: Operating System :: MacOS
Classifier: License :: OSI Approved :: BSD License
Classifier: Topic :: Scientific/Engineering
Classifier: Topic :: Scientific/Engineering :: Image Processing
Classifier: Topic :: Scientific/Engineering :: Visualization
Classifier: Topic :: Software Development :: Libraries :: Java Libraries
Classifier: Topic :: Software Development :: Libraries :: Python Modules
Requires-Python: <3.13,>=3.9
License-File: LICENSE
Requires-Dist: confuse>=2.0.0
Requires-Dist: imglyb>=2.1.0
Requires-Dist: jpype1>=1.4.1
Requires-Dist: labeling>=0.1.12
Requires-Dist: magicgui>=0.5.1
Requires-Dist: napari>=0.4.17
Requires-Dist: numpy
Requires-Dist: pandas
Requires-Dist: pyimagej>=1.4.1
Requires-Dist: scyjava>=1.9.1
Requires-Dist: superqt>=0.7.0
Requires-Dist: xarray<2024.10.0
Requires-Dist: qtconsole!=5.4.2
Requires-Dist: typing_extensions!=4.6.0
Provides-Extra: dev
Requires-Dist: build; extra == "dev"
Requires-Dist: myst-parser; extra == "dev"
Requires-Dist: pre-commit; extra == "dev"
Requires-Dist: pyqt5; extra == "dev"
Requires-Dist: pytest; extra == "dev"
Requires-Dist: pytest-cov; extra == "dev"
Requires-Dist: pytest-env; extra == "dev"
Requires-Dist: pytest-qt; extra == "dev"
Requires-Dist: ruff; extra == "dev"
Requires-Dist: sphinx; extra == "dev"
Requires-Dist: sphinx-copybutton; extra == "dev"
Requires-Dist: sphinx-rtd-theme; extra == "dev"
Requires-Dist: qtpy; extra == "dev"
Requires-Dist: validate-pyproject[all]; extra == "dev"
